[
  {
    "py/object": "model.contact.Contact",
    "firstname": "",
    "middlename": "",
    "lastname": "",
    "nickname": "",
    "company": "",
    "address": "",
    "homepage": "",
    "email": "",
    "email2": "",
    "email3": "",
    "fax": "",
    "home": "",
    "mobile": "",
    "work": "",
    "bday": "",
    "bmonth": "-",
    "byear": "",
    "aday": "",
    "amonth": "-",
    "ayear": "",
    "address2": "",
    "phone2": "",
    "notes": "",
    "title": "",
    "photo": "",
    "id": null,
    "all_phones_from_home_page": null,
    "all_emails_from_home_page": null
  },
  {
    "py/object": "model.contact.Contact",
    "firstname": "firstnameN2K`",
    "middlename": "middlename",
    "lastname": "lastname]",
    "nickname": "nickname+ P(",
    "company": "company21x7 ;{9",
    "address": "address@*$",
    "homepage": "homepage[P#",
    "email": "K721.org",
    "email2": " a0Fqr9Y.com",
    "email3": "  @V.net",
    "fax": "faxba-q_HXSb",
    "home": "90793058753",
    "mobile": "28469336053",
    "work": "62258909544",
    "bday": "13",
    "bmonth": "April",
    "byear": 2004,
    "aday": "10",
    "amonth": "July",
    "ayear": 2007,
    "address2": "address2-l>_oc",
    "phone2": "28019752227",
    "notes": "notes58 X^z",
    "title": "title<~p6 3N",
    "photo": "C:\\Users\\79120\\PycharmProjects\\Mytest1\\scale_1200-15.jpg",
    "id": null,
    "all_phones_from_home_page": null,
    "all_emails_from_home_page": null
  },
  {
    "py/object": "model.contact.Contact",
    "firstname": "firstnameH,3:m",
    "middlename": "middlenamesapssVK",
    "lastname": "lastname H&=BzL$e",
    "nickname": "nickname ",
    "company": "company>7Q",
    "address": "address3!",
    "homepage": "homepageNBSx8p",
    "email": "Cdn@OMe.org",
    "email2": "bt ByHF@s jg *.org",
    "email3": "O4k j@E .net",
    "fax": "faxn",
    "home": "01813153408",
    "mobile": "28677948139",
    "work": "48101564116",
    "bday": "21",
    "bmonth": "September",
    "byear": 2007,
    "aday": "26",
    "amonth": "May",
    "ayear": 2002,
    "address2": "address2_K",
    "phone2": "08840752196",
    "notes": "notesWC7VOE",
    "title": "title 2f ",
    "photo": "C:\\Users\\79120\\PycharmProjects\\Mytest1\\scale_1200-15.jpg",
    "id": null,
    "all_phones_from_home_page": null,
    "all_emails_from_home_page": null
  },
  {
    "py/object": "model.contact.Contact",
    "firstname": "firstnameO",
    "middlename": "middlename@",
    "lastname": "lastnameW ",
    "nickname": "nicknameMvUlO[G&",
    "company": "companyK9 -[6e",
    "address": "addresswE ",
    "homepage": "homepage3P2",
    "email": ".fs9ma @;d i.ru",
    "email2": "m@}J.org",
    "email3": "*@2Hm.com",
    "fax": "fax )ic(zvB",
    "home": "06813156144",
    "mobile": "13013188740",
    "work": "93969633641",
    "bday": "2",
    "bmonth": "April",
    "byear": 1994,
    "aday": "4",
    "amonth": "August",
    "ayear": 2004,
    "address2": "address2",
    "phone2": "87476749683",
    "notes": "notes*%",
    "title": "title8W",
    "photo": "C:\\Users\\79120\\PycharmProjects\\Mytest1\\scale_1200-15.jpg",
    "id": null,
    "all_phones_from_home_page": null,
    "all_emails_from_home_page": null
  },
  {
    "py/object": "model.contact.Contact",
    "firstname": "firstnamexE b",
    "middlename": "middlename6",
    "lastname": "lastnamer",
    "nickname": "nickname0",
    "company": "company3zB  36",
    "address": "address#^wpWP",
    "homepage": "homepage",
    "email": "d:je@j$IU%[bT.net",
    "email2": " L [@9]GO[Pzs.com",
    "email3": "L= | @k!oQ wf].com",
    "fax": "fax2-;f6(y-",
    "home": "90647727329",
    "mobile": "47705560459",
    "work": "23648800264",
    "bday": "24",
    "bmonth": "December",
    "byear": 1992,
    "aday": "13",
    "amonth": "August",
    "ayear": 1994,
    "address2": "address2  qw",
    "phone2": "68181194757",
    "notes": "notes",
    "title": "title8o5c4B U",
    "photo": "C:\\Users\\79120\\PycharmProjects\\Mytest1\\scale_1200-15.jpg",
    "id": null,
    "all_phones_from_home_page": null,
    "all_emails_from_home_page": null
  },
  {
    "py/object": "model.contact.Contact",
    "firstname": "firstnamew",
    "middlename": "middlename7$$U3:.",
    "lastname": "lastname",
    "nickname": "nicknameza-t2M",
    "company": "companyB?m)",
    "address": "address* m;h",
    "homepage": "homepage|33j<Od J",
    "email": "u D_sX@EbQ{ pI .ru",
    "email2": "V|zXS@+sa#.org",
    "email3": "UsgxSM@6.com",
    "fax": "faxLvPf_w[R",
    "home": "32940745913",
    "mobile": "24135312442",
    "work": "56085263417",
    "bday": "12",
    "bmonth": "October",
    "byear": 2011,
    "aday": "22",
    "amonth": "September",
    "ayear": 2017,
    "address2": "address28v_T)",
    "phone2": "73040076806",
    "notes": "notesW=",
    "title": "title,I7U",
    "photo": "C:\\Users\\79120\\PycharmProjects\\Mytest1\\scale_1200-15.jpg",
    "id": null,
    "all_phones_from_home_page": null,
    "all_emails_from_home_page": null
  }
]